PSetTweaks/PSetTweak.py
PSetTweaks/WMTweak.py
PSetTweaks/__init__.py
Utils/CPMetrics.py
Utils/CertTools.py
Utils/EmailAlert.py
Utils/ExtendedUnitTestCase.py
Utils/FileTools.py
Utils/IteratorTools.py
Utils/MathUtils.py
Utils/MemoryCache.py
Utils/Patterns.py
Utils/Pipeline.py
Utils/PortForward.py
Utils/ProcFS.py
Utils/ProcessStats.py
Utils/PythonVersion.py
Utils/Signals.py
Utils/TemporaryEnvironment.py
Utils/Throttled.py
Utils/Timers.py
Utils/Timestamps.py
Utils/TokenManager.py
Utils/Tracing.py
Utils/TwPrint.py
Utils/Utilities.py
Utils/__init__.py
Utils/wmcoreDTools.py
WMComponent/__init__.py
WMComponent/AgentStatusWatcher/AgentStatusPoller.py
WMComponent/AgentStatusWatcher/AgentStatusWatcher.py
WMComponent/AgentStatusWatcher/DrainStatusAPI.py
WMComponent/AgentStatusWatcher/DrainStatusPoller.py
WMComponent/AgentStatusWatcher/ResourceControlUpdater.py
WMComponent/AgentStatusWatcher/__init__.py
WMComponent/AgentWatchdog/AgentWatchdog.py
WMComponent/AgentWatchdog/AgentWatchdogPoller.py
WMComponent/AgentWatchdog/AgentWatchdogScanner.py
WMComponent/AgentWatchdog/Timer.py
WMComponent/AnalyticsDataCollector/AnalyticsDataCollector.py
WMComponent/AnalyticsDataCollector/AnalyticsPoller.py
WMComponent/AnalyticsDataCollector/DataCollectAPI.py
WMComponent/AnalyticsDataCollector/DataCollectorEmulatorSwitch.py
WMComponent/AnalyticsDataCollector/__init__.py
WMComponent/AnalyticsDataCollector/Plugins/PluginInterface.py
WMComponent/AnalyticsDataCollector/Plugins/Tier0Plugin.py
WMComponent/AnalyticsDataCollector/Plugins/__init__.py
WMComponent/ArchiveDataReporter/ArchiveDataPoller.py
WMComponent/ArchiveDataReporter/ArchiveDataReporter.py
WMComponent/ArchiveDataReporter/__init__.py
WMComponent/DBS3Buffer/DBS3Upload.py
WMComponent/DBS3Buffer/DBSBufferBlock.py
WMComponent/DBS3Buffer/DBSBufferDataset.py
WMComponent/DBS3Buffer/DBSBufferFile.py
WMComponent/DBS3Buffer/DBSBufferUtil.py
WMComponent/DBS3Buffer/DBSUploadPoller.py
WMComponent/DBS3Buffer/__init__.py
wmagent-2.4.5.2.dist-info/licenses/LICENSE
wmagent-2.4.5.2.dist-info/licenses/NOTICE
wmagent-2.4.5.2.dist-info/METADATA
wmagent-2.4.5.2.dist-info/WHEEL
wmagent-2.4.5.2.dist-info/top_level.txt
wmagent-2.4.5.2.dist-info/RECORD
