Metadata-Version: 2.4
Name: wmagent
Version: 2.4.5.2
Home-page: https://github.com/dmwm/WMCore
Maintainer: CMS DMWM Group
Maintainer-email: hn-cms-wmdevelopment@cern.ch
License: Apache License, Version 2.0
License-File: LICENSE
License-File: NOTICE
Requires-Dist: CT3~=3.4.0
Requires-Dist: CherryPy~=18.10.0
Requires-Dist: CMSCouchapp~=1.3.4
Requires-Dist: CMSMonitoring~=0.6.13
Requires-Dist: coverage~=7.9.0
Requires-Dist: oracledb~=3.3.0
Requires-Dist: dbs3-client==4.0.19
Requires-Dist: future~=1.0.0
Requires-Dist: httplib2~=0.22.0
Requires-Dist: htcondor~=25.0.3
Requires-Dist: Jinja2~=3.1.6
Requires-Dist: mock~=5.2.0
Requires-Dist: mysqlclient~=2.1.1
Requires-Dist: psutil~=7.0.0
Requires-Dist: pycurl~=7.45.6
Requires-Dist: pyOpenSSL~=25.1.0
Requires-Dist: pyzmq~=27.0.1
Requires-Dist: retry~=0.9.2
Requires-Dist: rucio-clients~=36.5.0
Requires-Dist: Sphinx~=5.3.0
Requires-Dist: SQLAlchemy~=1.4.54
Requires-Dist: PyJWT~=2.9.0
Requires-Dist: requests~=2.32.4
Requires-Dist: wmcoredb>=0.9.3
Requires-Dist: python-ptrace~=0.9.9
Dynamic: home-page
Dynamic: license
Dynamic: license-file
Dynamic: maintainer
Dynamic: maintainer-email
Dynamic: requires-dist
